{
	"lineName": "エンデル鉄道ドレッジ線",
	"lineColor": "#4169e1",
	"number": "103",
	"stations": [
		{
			"label": "ドレッジ",
			"pos": {
				"x": -264.412,
				"y": 81.802
			},
			"type": "middle"
		},
		{
			"label": "東ドレッジ",
			"pos": {
				"x": -264.230,
				"y": 82.021
			},
			"type": "local"
		},
		{
			"label": "ヂロン",
			"pos": {
				"x": -264.060,
				"y": 82.349
			},
			"type": "local"
		},
		{
			"label": "ギカニニン",
			"pos": {
				"x": -263.894,
				"y": 82.742
			},
			"type": "local"
		},
		{
			"label": "ニセラア",
			"pos": {
				"x": -263.828,
				"y": 83.261
			},
			"type": "local"
		},
		{
			"label": "ラルセン",
			"pos": {
				"x": -263.765,
				"y": 84.253
			},
			"type": "local"
		},
		{
			"label": "東ラルセン",
			"pos": {
				"x": -263.789,
				"y": 84.558
			},
			"type": "local"
		},
		{
			"label": "ダラヘビ",
			"pos": {
				"x": -263.803,
				"y": 85.062
			},
			"type": "middle"
		},
		{
			"label": "東ダラヘビ",
			"pos": {
				"x": -263.787,
				"y": 85.364
			},
			"type": "local"
		},
		{
			"label": "ネビンネ",
			"pos": {
				"x": -263.800,
				"y": 85.845
			},
			"type": "local"
		},
		{
			"label": "ネビン",
			"pos": {
				"x": -263.810,
				"y": 86.231
			},
			"type": "local"
		},
		{
			"label": "ネセ",
			"pos": {
				"x": -263.961,
				"y": 87.108
			},
			"type": "local"
		},
		{
			"label": "レハアドネ",
			"pos": {
				"x": -264.219,
				"y": 87.800
			},
			"type": "local"
		},
		{
			"label": "ヅユバヌ",
			"pos": {
				"x": -264.406,
				"y": 88.350
			},
			"type": "local"
		},
		{
			"label": "エッテ樹林",
			"pos": {
				"x": -264.597,
				"y": 88.963
			},
			"type": "local"
		},
		{
			"label": "エッテ町",
			"pos": {
				"x": -264.687,
				"y": 89.483
			},
			"type": "middle"
		},
		{
			"label": "テメルネ高原",
			"pos": {
				"x": -265.332,
				"y": 90.670
			},
			"type": "local"
		},
		{
			"label": "テメルネ",
			"pos": {
				"x": -265.601,
				"y": 91.299
			},
			"type": "local"
		},
		{
			"label": "東テメルネ",
			"pos": {
				"x": -265.757,
				"y": 91.627
			},
			"type": "local"
		},
		{
			"label": "ニヒンニヒ",
			"pos": {
				"x": -266.284,
				"y": 92.494
			},
			"type": "local"
		},
		{
			"label": "北グゼルゼニ",
			"pos": {
				"x": -266.621,
				"y": 92.929
			},
			"type": "local"
		},
		{
			"label": "グラド",
			"pos": {
				"x": -266.726,
				"y": 93.164
			},
			"type": "main"
		},
		{
			"label": "南グラド",
			"pos": {
				"x": -266.910,
				"y": 93.450
			},
			"type": "local"
		},
		{
			"label": "ヲゴリン丘",
			"pos": {
				"x": -267.454,
				"y": 93.970
			},
			"type": "local"
		},
		{
			"label": "シベフォン",
			"pos": {
				"x": -268.090,
				"y": 94.407
			},
			"type": "local"
		},
		{
			"label": "ワノドグレ",
			"pos": {
				"x": -268.453,
				"y": 94.706
			},
			"type": "local"
		},
		{
			"label": "エル峠",
			"pos": {
				"x": -269.203,
				"y": 95.308
			},
			"type": "local"
		},
		{
			"label": "エルネン",
			"pos": {
				"x": -269.878,
				"y": 96.026
			},
			"type": "local"
		},
		{
			"label": "ムルマンス",
			"pos": {
				"x": -270.093,
				"y": 96.308
			},
			"type": "local"
		},
		{
			"label": "フィニキア",
			"pos": {
				"x": -270.511,
				"y": 97.092
			},
			"type": "main"
		}
	]
}